psort/OpenEphys.py
psort/__init__.py
psort/database.py
psort/edit_prefrences.py
psort/inputDialog.py
psort/lib.py
psort/main.py
psort/scatterSelect.py
psort/slotBoundary.py
psort/update_to_psort04.py
psort/utils.py
psort/waveDissect.py
psort/config/gui_config.yml
psort/gui/__init__.py
psort/gui/signals.py
psort/gui/widgets.py
psort/icon/023-download-blue.png
psort/icon/023-download-red.png
psort/icon/029-folder.png
psort/icon/030-forbidden-blue.png
psort/icon/030-forbidden-red.png
psort/icon/036-left-arrow.png
psort/icon/067-trash-blue.png
psort/icon/067-trash-red.png
psort/icon/068-recycling.png
psort/icon/068-redo.png
psort/icon/068-undo.png
psort/icon/071-right-arrow.png
psort/icon/073-diskette.png
psort/icon/084-shuffle-left-red.png
psort/icon/084-shuffle-right-blue.png
psort/icon/clear.png
psort/icon/crosshair.png
psort/icon/delete.png
psort/icon/marmoset.png
psort/icon/move.png
psort/icon/next_spike.png
psort/icon/next_window.png
psort/icon/previous_spike.png
psort/icon/previous_window.png
psort/icon/range.png
psort/icon/select.png
psort/icon/toggle.png
psort/icon/zoom_in.png
psort/icon/zoom_out.png
psort/icons/023-download-blue.png
psort/icons/023-download-red.png
psort/icons/029-folder.png
psort/icons/030-forbidden-blue.png
psort/icons/030-forbidden-red.png
psort/icons/036-left-arrow.png
psort/icons/067-trash-blue.png
psort/icons/067-trash-red.png
psort/icons/068-recycling.png
psort/icons/068-redo.png
psort/icons/068-undo.png
psort/icons/071-right-arrow.png
psort/icons/073-diskette.png
psort/icons/084-shuffle-left-red.png
psort/icons/084-shuffle-right-blue.png
psort/icons/clear.png
psort/icons/crosshair.png
psort/icons/delete.png
psort/icons/marmoset.png
psort/icons/move.png
psort/icons/next_spike.png
psort/icons/next_window.png
psort/icons/previous_spike.png
psort/icons/previous_window.png
psort/icons/range.png
psort/icons/select.png
psort/icons/toggle.png
psort/icons/zoom_in.png
psort/icons/zoom_out.png
psort/tests/__init__.py
psort-0.4.26.dist-info/LICENSE
psort-0.4.26.dist-info/METADATA
psort-0.4.26.dist-info/WHEEL
psort-0.4.26.dist-info/entry_points.txt
psort-0.4.26.dist-info/top_level.txt
psort-0.4.26.dist-info/RECORD
